fri_oo/__init__.py
fri_oo/alg_tools_1d.py
fri_oo/alg_tools_2d.py
fri_oo/fri_curve.py
fri_oo/irr_four_samp.py
fri_oo/irr_time_samp.py
fri_oo/plotter.py
fri_oo/simulation.py
fri_oo-1.0.1.dist-info/METADATA
fri_oo-1.0.1.dist-info/WHEEL
fri_oo-1.0.1.dist-info/top_level.txt
fri_oo-1.0.1.dist-info/RECORD
